authentik_client/__init__.py
authentik_client/api_client.py
authentik_client/api_response.py
authentik_client/configuration.py
authentik_client/exceptions.py
authentik_client/py.typed
authentik_client/rest.py
authentik_client/api/__init__.py
authentik_client/api/admin_api.py
authentik_client/api/authenticators_api.py
authentik_client/api/core_api.py
authentik_client/api/crypto_api.py
authentik_client/api/enterprise_api.py
authentik_client/api/events_api.py
authentik_client/api/flows_api.py
authentik_client/api/managed_api.py
authentik_client/api/oauth2_api.py
authentik_client/api/outposts_api.py
authentik_client/api/policies_api.py
authentik_client/api/propertymappings_api.py
authentik_client/api/providers_api.py
authentik_client/api/rac_api.py
authentik_client/api/rbac_api.py
authentik_client/api/root_api.py
authentik_client/api/schema_api.py
authentik_client/api/sources_api.py
authentik_client/api/ssf_api.py
authentik_client/api/stages_api.py
authentik_client/api/tasks_api.py
authentik_client/api/tenants_api.py
authentik_client/models/__init__.py
authentik_client/models/access_denied_challenge.py
authentik_client/models/alg_enum.py
authentik_client/models/app.py
authentik_client/models/app_enum.py
authentik_client/models/apple_challenge_response_request.py
authentik_client/models/apple_login_challenge.py
authentik_client/models/application.py
authentik_client/models/application_entitlement.py
authentik_client/models/application_entitlement_request.py
authentik_client/models/application_request.py
authentik_client/models/auth_mode_enum.py
authentik_client/models/auth_type_enum.py
authentik_client/models/authenticated_session.py
authentik_client/models/authenticated_session_asn.py
authentik_client/models/authenticated_session_geo_ip.py
authentik_client/models/authenticated_session_user_agent.py
authentik_client/models/authenticated_session_user_agent_device.py
authentik_client/models/authenticated_session_user_agent_os.py
authentik_client-2025.8.4.dist-info/licenses/LICENSE
authentik_client-2025.8.4.dist-info/METADATA
authentik_client-2025.8.4.dist-info/WHEEL
authentik_client-2025.8.4.dist-info/top_level.txt
authentik_client-2025.8.4.dist-info/RECORD
