Metadata-Version: 2.4
Name: authentik_client
Version: 2025.8.4
Summary: authentik
Home-page: 
Author: authentik Team
Author-email: authentik Team <hello@goauthentik.io>
License-Expression: MIT
Project-URL: Repository, https://github.com/GIT_USER_ID/GIT_REPO_ID
Keywords: OpenAPI,OpenAPI-Generator,authentik
Requires-Python: >=3.9
License-File: LICENSE
Requires-Dist: urllib3<3.0.0,>=2.1.0
Requires-Dist: python-dateutil>=2.8.2
Requires-Dist: pydantic>=2
Requires-Dist: typing-extensions>=4.7.1
Requires-Dist: lazy-imports<2,>=1
Dynamic: author
Dynamic: license-file
